calculation2/__init__.py
calculation2/button_names.py
calculation2/calculator.py
calculation2/calculator_date.py
calculation2/calculator_date_page.py
calculation2/calculator_page.py
calculation2/calculator_standard_science.py
calculation2/programmer_page.py
calculation2/science_page.py
calculation2/standard_page.py
tests/__init__.py
calculation2-2.1.0.dist-info/LICENSE
calculation2-2.1.0.dist-info/METADATA
calculation2-2.1.0.dist-info/WHEEL
calculation2-2.1.0.dist-info/top_level.txt
calculation2-2.1.0.dist-info/RECORD
